{
    "tenantId": "pg",
    "moduleName": "FSM",
    "CancelReason": [
        {
            "name": "Duplicate application",
            "code": "DUPLICATE",
            "active": true
        },
        {
            "name": "Not able to contact applicant",
            "code": "CANNOT_CONTACT_APPLICANT",
            "active": true
        },
        {
            "name": "Citizen Denied Request",
            "code": "CITIZEN_DENIED_REQUEST",
            "active": true
        },
        {
            "name": "Others",
            "code": "OTHERS",
            "active": true
        }
    ]
}