{
    "tenantId": "pg",
    "moduleName": "FSM",
    "SanitationType": [
        {
            "name": "Conventional septic tanks with single pit",
            "code": "CONVENTIONAL_SINGLE_PIT",
            "active": true
        },
        {
            "name": "Conventional septic tank with dual pit",
            "code": "CONVENTIONAL_DUAL_PIT",
            "active": true
        },
        {
            "name": "Improved septic tank - Upflow Anaerabic filter",
            "code": "IMPROVED_UPFLOW",
            "active": true
        },
        {
            "name": "Improved septic tank - Packaged contact aeration type",
            "code": "IMPROVED_PACKED",
            "active": true
        },
        {
            "name": "Johakasu systems",
            "code": "JOHAKASU_SYSTEMS",
            "active": true
        },
        {
            "name": "Bio digester",
            "code": "BIO_DIGESTER",
            "active": true
        }
    ]
}