{
  "tenantId": "pb.alawalpur",
  "moduleName": "egov-location",
  "TenantBoundary": [
    {
      "hierarchyType": {
        "code": "ADMIN",
        "name": "ADMIN"
      },
      "boundary": {
        "id": 1,
        "boundaryNum": 1,
        "name": "Alawalpur",
        "localname": "Alawalpur",
        "longitude": null,
        "latitude": null,
        "label": "City",
        "code": "pb.alawalpur",
        "children": [
          {
            "id": "b614c20e-3553-45cc-88da-0b453bbb2164",
            "boundaryNum": 1,
            "name": "ALAWALPUR",
            "localname": "ALAWALPUR",
            "longitude": null,
            "latitude": null,
            "label": "Zone",
            "code": "ALA1",
            "children": [
              {
                "id": "449a5d58-70fa-4ea2-b7e3-43ddeb289b79",
                "boundaryNum": 1,
                "name": "WARD - 1",
                "localname": "WARD - 1",
                "longitude": null,
                "latitude": null,
                "label": "Block",
                "code": "Ward 1",
                "children": [
                  {
                    "id": "154bf72e-f718-47f3-b4fb-de19d2c2cfda",
                    "boundaryNum": 1,
                    "name": "Julaha",
                    "localname": "Julaha",
                    "longitude": null,
                    "latitude": null,
                    "label": "Locality",
                    "code": "ALA1",
                    "area": "",
                    "children": []
                  },
                  {
                    "id": "be5def97-745e-401f-aed6-66e102c53b9d",
                    "boundaryNum": 1,
                    "name": "Beaspind road",
                    "localname": "Beaspind road",
                    "longitude": null,
                    "latitude": null,
                    "label": "Locality",
                    "code": "ALA2",
                    "area": "",
                    "children": []
                  },
                  {
                    "id": "a7e7abf8-96b5-4a5f-a300-7a9d2768ef0f",
                    "boundaryNum": 1,
                    "name": "Main Bazar",
                    "localname": "Main Bazar",
                    "longitude": null,
                    "latitude": null,
                    "label": "Locality",
                    "code": "ALA3",
                    "area": "",
                    "children": []
                  }
                ]
              },
              {
                "id": "a2f20926-a436-4b09-b3e2-ba26868033b1",
                "boundaryNum": 1,
                "name": "WARD - 2",
                "localname": "WARD - 2",
                "longitude": null,
                "latitude": null,
                "label": "Block",
                "code": "Ward 2",
                "children": [
                  {
                    "id": "c0bd1aa4-e687-4db5-8f94-e17a7ce1026e",
                    "boundaryNum": 1,
                    "name": "Tawela",
                    "localname": "Tawela",
                    "longitude": null,
                    "latitude": null,
                    "label": "Locality",
                    "code": "ALA4",
                    "area": "",
                    "children": []
                  },
                  {
                    "id": "7c3e6e96-475b-4521-aa89-6c3f0651b702",
                    "boundaryNum": 1,
                    "name": "Ramgarhia",
                    "localname": "Ramgarhia",
                    "longitude": null,
                    "latitude": null,
                    "label": "Locality",
                    "code": "ALA5",
                    "area": "",
                    "children": []
                  },
                  {
                    "id": "9d02858b-a0ac-4b3a-8b29-a39d39c09228",
                    "boundaryNum": 1,
                    "name": "kila",
                    "localname": "kila",
                    "longitude": null,
                    "latitude": null,
                    "label": "Locality",
                    "code": "ALA6",
                    "area": "",
                    "children": []
                  },
                  {
                    "id": "9897aa25-f526-4bec-b33c-c8a97979d979",
                    "boundaryNum": 1,
                    "name": "Chodha",
                    "localname": "Chodha",
                    "longitude": null,
                    "latitude": null,
                    "label": "Locality",
                    "code": "ALA7",
                    "area": "",
                    "children": []
                  }
                ]
              },
              {
                "id": "9945e6bf-74fc-49be-acd9-8e980d330eae",
                "boundaryNum": 1,
                "name": "WARD - 3",
                "localname": "WARD - 3",
                "longitude": null,
                "latitude": null,
                "label": "Block",
                "code": "Ward 3",
                "children": [
                  {
                    "id": "9133793f-3968-4b02-9c8f-4231567d485c",
                    "boundaryNum": 1,
                    "name": "Rishi Nagar",
                    "localname": "Rishi Nagar",
                    "longitude": null,
                    "latitude": null,
                    "label": "Locality",
                    "code": "ALA8",
                    "area": "",
                    "children": []
                  },
                  {
                    "id": "42481ad1-132c-42d2-8275-7ed645c220dc",
                    "boundaryNum": 1,
                    "name": "Balmiki",
                    "localname": "Balmiki",
                    "longitude": null,
                    "latitude": null,
                    "label": "Locality",
                    "code": "ALA9",
                    "area": "",
                    "children": []
                  }
                ]
              },
              {
                "id": "e3eb60b4-95d8-4089-82b0-04d8932e1da6",
                "boundaryNum": 1,
                "name": "WARD - 4",
                "localname": "WARD - 4",
                "longitude": null,
                "latitude": null,
                "label": "Block",
                "code": "Ward 4",
                "children": [
                  {
                    "id": "f23ff4e3-7611-4431-9ed2-5ef1391d52d9",
                    "boundaryNum": 1,
                    "name": "Thathi",
                    "localname": "Thathi",
                    "longitude": null,
                    "latitude": null,
                    "label": "Locality",
                    "code": "ALA10",
                    "area": "",
                    "children": []
                  },
                  {
                    "id": "6028bc45-c644-4d80-b44a-011d6ccc95d3",
                    "boundaryNum": 1,
                    "name": "Kundan Virdh Ashrama",
                    "localname": "Kundan Virdh Ashrama",
                    "longitude": null,
                    "latitude": null,
                    "label": "Locality",
                    "code": "ALA11",
                    "area": "",
                    "children": []
                  },
                  {
                    "id": "e6329a75-7fb8-483b-bab1-3e254e048d6a",
                    "boundaryNum": 1,
                    "name": "Shahparwana",
                    "localname": "Shahparwana",
                    "longitude": null,
                    "latitude": null,
                    "label": "Locality",
                    "code": "ALA12",
                    "area": "",
                    "children": []
                  },
                  {
                    "id": "e56bbae7-6ee6-4845-9ca3-02b26ca5d3fb",
                    "boundaryNum": 1,
                    "name": "Navipur",
                    "localname": "Navipur",
                    "longitude": null,
                    "latitude": null,
                    "label": "Locality",
                    "code": "ALA13",
                    "area": "",
                    "children": []
                  },
                  {
                    "id": "48fa7f18-d750-4dcf-be1f-a45d9f1be2dd",
                    "boundaryNum": 1,
                    "name": "Ramdasspur",
                    "localname": "Ramdasspur",
                    "longitude": null,
                    "latitude": null,
                    "label": "Locality",
                    "code": "ALA14",
                    "area": "",
                    "children": []
                  }
                ]
              },
              {
                "id": "b1c0c520-9cb3-4a68-98ae-07aecab7b4d6",
                "boundaryNum": 1,
                "name": "WARD - 5",
                "localname": "WARD - 5",
                "longitude": null,
                "latitude": null,
                "label": "Block",
                "code": "Ward 5",
                "children": [
                  {
                    "id": "5cbd4ff7-d5d2-4438-b8fb-08a89c1d213d",
                    "boundaryNum": 1,
                    "name": "Ramdasspur",
                    "localname": "Ramdasspur",
                    "longitude": null,
                    "latitude": null,
                    "label": "Locality",
                    "code": "ALA15",
                    "area": "",
                    "children": []
                  }
                ]
              },
              {
                "id": "f68ec376-c163-4627-ba22-25d0db8f36f3",
                "boundaryNum": 1,
                "name": "WARD - 6",
                "localname": "WARD - 6",
                "longitude": null,
                "latitude": null,
                "label": "Block",
                "code": "Ward 6",
                "children": [
                  {
                    "id": "2ce333be-7c6a-4ba3-b081-b4abd38cd876",
                    "boundaryNum": 1,
                    "name": "Navipur",
                    "localname": "Navipur",
                    "longitude": null,
                    "latitude": null,
                    "label": "Locality",
                    "code": "ALA16",
                    "area": "",
                    "children": []
                  },
                  {
                    "id": "9df6e51b-5882-4c2c-998b-8064664b4521",
                    "boundaryNum": 1,
                    "name": "Ramdasspur",
                    "localname": "Ramdasspur",
                    "longitude": null,
                    "latitude": null,
                    "label": "Locality",
                    "code": "ALA17",
                    "area": "",
                    "children": []
                  },
                  {
                    "id": "bdc14fa5-6b30-464d-9a1e-727fb16a5b49",
                    "boundaryNum": 1,
                    "name": "Lesariwal road",
                    "localname": "Lesariwal road",
                    "longitude": null,
                    "latitude": null,
                    "label": "Locality",
                    "code": "ALA18",
                    "area": "",
                    "children": []
                  }
                ]
              },
              {
                "id": "4c158a98-b7d7-4df0-9195-d01f39e740bd",
                "boundaryNum": 1,
                "name": "WARD - 7",
                "localname": "WARD - 7",
                "longitude": null,
                "latitude": null,
                "label": "Block",
                "code": "Ward 7",
                "children": [
                  {
                    "id": "c7b8a278-b7c6-4b72-92fa-2ba7f7881b59",
                    "boundaryNum": 1,
                    "name": "Sariha",
                    "localname": "Sariha",
                    "longitude": null,
                    "latitude": null,
                    "label": "Locality",
                    "code": "ALA19",
                    "area": "",
                    "children": []
                  },
                  {
                    "id": "24ac2acd-f4e6-40f1-95ea-9b19864e1969",
                    "boundaryNum": 1,
                    "name": "Mishra",
                    "localname": "Mishra",
                    "longitude": null,
                    "latitude": null,
                    "label": "Locality",
                    "code": "ALA20",
                    "area": "",
                    "children": []
                  },
                  {
                    "id": "ee7744f7-1199-47f2-9cd1-8fb5d71db3b1",
                    "boundaryNum": 1,
                    "name": "Navipur",
                    "localname": "Navipur",
                    "longitude": null,
                    "latitude": null,
                    "label": "Locality",
                    "code": "ALA21",
                    "area": "",
                    "children": []
                  },
                  {
                    "id": "e132aff7-3ea1-4783-b5e0-3a7002a3b868",
                    "boundaryNum": 1,
                    "name": "Handa",
                    "localname": "Handa",
                    "longitude": null,
                    "latitude": null,
                    "label": "Locality",
                    "code": "ALA22",
                    "area": "",
                    "children": []
                  }
                ]
              },
              {
                "id": "ff9e5372-8777-4f8c-aa55-d0d95a48dcc6",
                "boundaryNum": 1,
                "name": "WARD - 8",
                "localname": "WARD - 8",
                "longitude": null,
                "latitude": null,
                "label": "Block",
                "code": "Ward 8",
                "children": [
                  {
                    "id": "056638a9-64aa-4696-afe8-c5c1f72374bd",
                    "boundaryNum": 1,
                    "name": "Jhanda Sahib",
                    "localname": "Jhanda Sahib",
                    "longitude": null,
                    "latitude": null,
                    "label": "Locality",
                    "code": "ALA23",
                    "area": "",
                    "children": []
                  },
                  {
                    "id": "3c9fd38c-49b2-4085-a992-ad3ee7feebd3",
                    "boundaryNum": 1,
                    "name": "Mishra",
                    "localname": "Mishra",
                    "longitude": null,
                    "latitude": null,
                    "label": "Locality",
                    "code": "ALA24",
                    "area": "",
                    "children": []
                  },
                  {
                    "id": "89121463-fda0-4a97-b275-ae166d0edb0d",
                    "boundaryNum": 1,
                    "name": "Chatti Gali",
                    "localname": "Chatti Gali",
                    "longitude": null,
                    "latitude": null,
                    "label": "Locality",
                    "code": "ALA25",
                    "area": "",
                    "children": []
                  },
                  {
                    "id": "4cb4d11b-d9cc-4420-bd9f-ee14b9b5784e",
                    "boundaryNum": 1,
                    "name": "Main Bazar",
                    "localname": "Main Bazar",
                    "longitude": null,
                    "latitude": null,
                    "label": "Locality",
                    "code": "ALA26",
                    "area": "",
                    "children": []
                  }
                ]
              },
              {
                "id": "e03e132a-5814-4308-a665-a75621bb9477",
                "boundaryNum": 1,
                "name": "WARD - 9",
                "localname": "WARD - 9",
                "longitude": null,
                "latitude": null,
                "label": "Block",
                "code": "Ward 9",
                "children": [
                  {
                    "id": "7353b6cf-6a62-4076-85bb-6e387bc4e169",
                    "boundaryNum": 1,
                    "name": "Prem Nagar",
                    "localname": "Prem Nagar",
                    "longitude": null,
                    "latitude": null,
                    "label": "Locality",
                    "code": "ALA27",
                    "area": "",
                    "children": []
                  },
                  {
                    "id": "fbcdde8a-370c-4c05-8128-4c9e11b82753",
                    "boundaryNum": 1,
                    "name": "Ahluwalia",
                    "localname": "Ahluwalia",
                    "longitude": null,
                    "latitude": null,
                    "label": "Locality",
                    "code": "ALA28",
                    "area": "",
                    "children": []
                  },
                  {
                    "id": "8a419d96-8450-471c-a8cb-502e1d1ad122",
                    "boundaryNum": 1,
                    "name": "Jhanda Sahib",
                    "localname": "Jhanda Sahib",
                    "longitude": null,
                    "latitude": null,
                    "label": "Locality",
                    "code": "ALA29",
                    "area": "",
                    "children": []
                  }
                ]
              },
              {
                "id": "8beff6be-3309-4eb5-a68d-6b4b871261c2",
                "boundaryNum": 1,
                "name": "WARD - 10",
                "localname": "WARD - 10",
                "longitude": null,
                "latitude": null,
                "label": "Block",
                "code": "Ward 10",
                "children": [
                  {
                    "id": "4593030c-2689-4739-8e2d-fcd6d6fa3da5",
                    "boundaryNum": 1,
                    "name": "New Model Town",
                    "localname": "New Model Town",
                    "longitude": null,
                    "latitude": null,
                    "label": "Locality",
                    "code": "ALA30",
                    "area": "",
                    "children": []
                  },
                  {
                    "id": "25f38be3-5c9b-4977-ac9a-2f1e2742300c",
                    "boundaryNum": 1,
                    "name": "Basant Vihar",
                    "localname": "Basant Vihar",
                    "longitude": null,
                    "latitude": null,
                    "label": "Locality",
                    "code": "ALA31",
                    "area": "",
                    "children": []
                  },
                  {
                    "id": "42038633-4183-44bb-bbd1-2d0febc0a498",
                    "boundaryNum": 1,
                    "name": "Chup Shah",
                    "localname": "Chup Shah",
                    "longitude": null,
                    "latitude": null,
                    "label": "Locality",
                    "code": "ALA32",
                    "area": "",
                    "children": []
                  }
                ]
              },
              {
                "id": "fe2ad74c-8de4-45f9-8239-20079fd13c1d",
                "boundaryNum": 1,
                "name": "WARD - 11",
                "localname": "WARD - 11",
                "longitude": null,
                "latitude": null,
                "label": "Block",
                "code": "Ward 11",
                "children": [
                  {
                    "id": "f86058de-a0e9-4216-828b-ad016aab9b85",
                    "boundaryNum": 1,
                    "name": "Parhidaya",
                    "localname": "Parhidaya",
                    "longitude": null,
                    "latitude": null,
                    "label": "Locality",
                    "code": "ALA33",
                    "area": "",
                    "children": []
                  },
                  {
                    "id": "fef8f1dd-81fd-4a87-88b1-48daeec22d29",
                    "boundaryNum": 1,
                    "name": "Sunder Nagar",
                    "localname": "Sunder Nagar",
                    "longitude": null,
                    "latitude": null,
                    "label": "Locality",
                    "code": "ALA34",
                    "area": "",
                    "children": []
                  }
                ]
              }
            ]
          }
        ]
      }
    },
    {
      "hierarchyType": {
        "code": "REVENUE",
        "name": "REVENUE"
      },
      "boundary": {
        "id": 1,
        "boundaryNum": 1,
        "name": "Alawalpur",
        "localname": "Alawalpur",
        "longitude": null,
        "latitude": null,
        "label": "City",
        "code": "pb.alawalpur",
        "children": [
          {
            "id": "06e52067-206d-4c9e-ba2e-2069c94c511b",
            "boundaryNum": 1,
            "name": "Zone 1",
            "localname": "Zone 1",
            "longitude": null,
            "latitude": null,
            "label": "Zone",
            "code": "Z1",
            "children": [
              {
                "id": "0d403b4b-49d5-42c0-9077-f0ac158fa32d",
                "boundaryNum": 1,
                "name": "Block 1",
                "localname": "Block 1",
                "longitude": null,
                "latitude": null,
                "label": "Block",
                "code": "B1",
                "children": [
                  {
                    "id": "8033aa92-6143-41ee-b39a-2c7d89221f18",
                    "boundaryNum": 1,
                    "name": "Main bazar - B1 - A1",
                    "localname": "Main bazar - B1 - A1",
                    "longitude": null,
                    "latitude": null,
                    "label": "Locality",
                    "code": "AL1",
                    "area": "AREA1",
                    "children": []
                  },
                  {
                    "id": "0cd3d208-2ccd-4fa1-bff4-246af66ea43c",
                    "boundaryNum": 1,
                    "name": "Kishangarh road - B1 - A1",
                    "localname": "Kishangarh road - B1 - A1",
                    "longitude": null,
                    "latitude": null,
                    "label": "Locality",
                    "code": "AL2",
                    "area": "AREA1",
                    "children": []
                  },
                  {
                    "id": "f275c450-4f5d-481a-a447-e87435b454bb",
                    "boundaryNum": 1,
                    "name": "Sikandpur road - B1 - A1",
                    "localname": "Sikandpur road - B1 - A1",
                    "longitude": null,
                    "latitude": null,
                    "label": "Locality",
                    "code": "AL3",
                    "area": "AREA1",
                    "children": []
                  },
                  {
                    "id": "7fe90c16-ac85-4d8b-9aed-441254a639cc",
                    "boundaryNum": 1,
                    "name": "Alawalpur  Adampur main road - B1 - A1",
                    "localname": "Alawalpur  Adampur main road - B1 - A1",
                    "longitude": null,
                    "latitude": null,
                    "label": "Locality",
                    "code": "AL4",
                    "area": "AREA1",
                    "children": []
                  },
                  {
                    "id": "c5f6c166-eaa7-4846-b9ae-c24c379bd0b4",
                    "boundaryNum": 1,
                    "name": "Beas Pind road,Alawalpur - B1 - A1",
                    "localname": "Beas Pind road,Alawalpur - B1 - A1",
                    "longitude": null,
                    "latitude": null,
                    "label": "Locality",
                    "code": "AL5",
                    "area": "AREA1",
                    "children": []
                  }
                ]
              },
              {
                "id": "c4f40c84-355b-42af-8951-e6f4d878e576",
                "boundaryNum": 1,
                "name": "Block 2",
                "localname": "Block 2",
                "longitude": null,
                "latitude": null,
                "label": "Block",
                "code": "B2",
                "children": [
                  {
                    "id": "1c9dac40-ad9c-4b87-98f4-da1212b9d9ee",
                    "boundaryNum": 1,
                    "name": "Mohalla Julaha, - B2 - A2",
                    "localname": "Mohalla Julaha, - B2 - A2",
                    "longitude": null,
                    "latitude": null,
                    "label": "Locality",
                    "code": "AL6",
                    "area": "AREA2",
                    "children": []
                  },
                  {
                    "id": "40c1cc3d-a313-4553-9eb1-39bada58ae83",
                    "boundaryNum": 1,
                    "name": "Mohalla Tawela,Bhandaria,Ramgarhia, Kila - B2 - A2",
                    "localname": "Mohalla Tawela,Bhandaria,Ramgarhia, Kila - B2 - A2",
                    "longitude": null,
                    "latitude": null,
                    "label": "Locality",
                    "code": "AL7",
                    "area": "AREA2",
                    "children": []
                  },
                  {
                    "id": "97a53626-3b05-4ba4-a10c-612390fe178f",
                    "boundaryNum": 1,
                    "name": "Mohalla Balmiki, Rishi Nagar - B2 - A2",
                    "localname": "Mohalla Balmiki, Rishi Nagar - B2 - A2",
                    "longitude": null,
                    "latitude": null,
                    "label": "Locality",
                    "code": "AL8",
                    "area": "AREA2",
                    "children": []
                  },
                  {
                    "id": "421d3e71-16fb-4c88-80f2-487a9941f4c2",
                    "boundaryNum": 1,
                    "name": "Mohalla Thathi,Shahparwana,Kundan Virdh Ashram - B2 - A2",
                    "localname": "Mohalla Thathi,Shahparwana,Kundan Virdh Ashram - B2 - A2",
                    "longitude": null,
                    "latitude": null,
                    "label": "Locality",
                    "code": "AL9",
                    "area": "AREA2",
                    "children": []
                  },
                  {
                    "id": "8515cad5-4d37-45c0-a773-25de387b0dce",
                    "boundaryNum": 1,
                    "name": "Mohalla Ramdasspur - B2 - A2",
                    "localname": "Mohalla Ramdasspur - B2 - A2",
                    "longitude": null,
                    "latitude": null,
                    "label": "Locality",
                    "code": "AL10",
                    "area": "AREA2",
                    "children": []
                  },
                  {
                    "id": "69f71be1-1355-4607-82f5-fbe5869d40e3",
                    "boundaryNum": 1,
                    "name": "Mohalla Navipur,lesariwal road - B2 - A2",
                    "localname": "Mohalla Navipur,lesariwal road - B2 - A2",
                    "longitude": null,
                    "latitude": null,
                    "label": "Locality",
                    "code": "AL11",
                    "area": "AREA2",
                    "children": []
                  },
                  {
                    "id": "8b3e2026-d0af-4943-b9e3-7955e678808e",
                    "boundaryNum": 1,
                    "name": "Mohalla Sarhia,Mishra,Geeta Bhawan - B2 - A2",
                    "localname": "Mohalla Sarhia,Mishra,Geeta Bhawan - B2 - A2",
                    "longitude": null,
                    "latitude": null,
                    "label": "Locality",
                    "code": "AL12",
                    "area": "AREA2",
                    "children": []
                  },
                  {
                    "id": "ca61d19f-1380-469d-a909-a98507fba56c",
                    "boundaryNum": 1,
                    "name": "Mohalla Janda Sahib,Padiya,Chatti Gali - B2 - A2",
                    "localname": "Mohalla Janda Sahib,Padiya,Chatti Gali - B2 - A2",
                    "longitude": null,
                    "latitude": null,
                    "label": "Locality",
                    "code": "AL13",
                    "area": "AREA2",
                    "children": []
                  },
                  {
                    "id": "e236dfdd-3dd3-41fd-a523-dbbea37f8f7f",
                    "boundaryNum": 1,
                    "name": "Mohalla Prem Nagar - B2 - A2",
                    "localname": "Mohalla Prem Nagar - B2 - A2",
                    "longitude": null,
                    "latitude": null,
                    "label": "Locality",
                    "code": "AL14",
                    "area": "AREA2",
                    "children": []
                  },
                  {
                    "id": "a4191998-526f-44ad-9a38-33c35d50cad4",
                    "boundaryNum": 1,
                    "name": "Mohalla New Model Town,Basant Vihar,Chup Shah - B2 - A2",
                    "localname": "Mohalla New Model Town,Basant Vihar,Chup Shah - B2 - A2",
                    "longitude": null,
                    "latitude": null,
                    "label": "Locality",
                    "code": "AL15",
                    "area": "AREA2",
                    "children": []
                  },
                  {
                    "id": "df631b3a-1088-4488-a514-65476ab65125",
                    "boundaryNum": 1,
                    "name": "Mohalla Sunder Nagar, Pahidiya - B2 - A2",
                    "localname": "Mohalla Sunder Nagar, Pahidiya - B2 - A2",
                    "longitude": null,
                    "latitude": null,
                    "label": "Locality",
                    "code": "AL16",
                    "area": "AREA2",
                    "children": []
                  }
                ]
              }
            ]
          }
        ]
      }
    }
  ]
}