{
  "tenantId": "mz",
  "moduleName": "hcm-microplanning",
  "UploadConfiguration": [
    {
      "id": "Population",
      "code": "POPULATION",
      "iconName": "Population",
      "UploadFileTypes": [
        {
          "id": "Excel",
          "code": "EXCEL",
          "fileExtension": ["xlsx", "xls"],
          "iconName": "Excel",
          "namingConvention": "(?i)^Population.xls(x)?$"
        },
        {
          "id": "Shapefile",
          "code": "SHAPE_FILES",
          "fileExtension": ["zip"],
          "iconName": "SpatialDocument",
          "namingConvention": "(?i)^Population.zip$"
        },
        {
          "id": "GeoJSON",
          "code": "GEOJSON",
          "fileExtension": ["geojson"],
          "iconName": "SpatialDocument",
          "namingConvention": "(?i)^Population.geojson$"
        }
      ]
    },
    {
      "id": "Facilities",
      "code": "FACILITIES",
      "iconName": "Facilities",
      "UploadFileTypes": [
        {
          "id": "Excel",
          "code": "EXCEL",
          "fileExtension": ["xlsx", "xls"],
          "iconName": "Excel",
          "namingConvention": "(?i)^Facilities.xls(x)?$"
        },
        {
          "id": "Shapefile",
          "code": "SHAPE_FILES",
          "fileExtension": ["zip"],
          "iconName": "SpatialDocument",
          "namingConvention": "(?i)^Facilities.zip$"
        },
        {
          "id": "GeoJSON",
          "code": "GEOJSON",
          "fileExtension": ["geojson"],
          "iconName": "SpatialDocument",
          "namingConvention": "(?i)^Facilities.geojson$"
        }
      ]
    }
  ]
}
