{
  "tenantId": "mz",
  "moduleName": "egov-location",
  "TenantBoundary": [
    {
      "hierarchyType": {
        "code": "ADMIN",
        "name": "ADMIN"
      },
      "boundary": {
        "id": "mz",
        "boundaryNum": 1,
        "name": "MOZAMBIQUE",
        "localname": "MOZAMBIQUE",
        "longitude": null,
        "latitude": null,
        "label": "Country",
        "code": "mz",
        "children": [
          {
            "id": "h65dbb180",
            "boundaryNum": 2,
            "name": "Nsadzon",
            "localname": "Nsadzon",
            "longitude": null,
            "latitude": null,
            "label": "Provincia",
            "code": "h65dbb180",
            "children": [
              {
                "id": "h5071ec3b",
                "boundaryNum": 3,
                "name": "Nsadzo sede",
                "localname": "Nsadzo sede",
                "longitude": null,
                "latitude": null,
                "label": "Posto Administrativo",
                "code": "h5071ec3b",
                "children": []
              }
            ]
          },
          {
            "id": "h5003f843",
            "boundaryNum": 2,
            "name": "Nsadzo",
            "localname": "Nsadzo",
            "longitude": null,
            "latitude": null,
            "label": "Provincia",
            "code": "h5003f843",
            "children": [
              {
                "id": "hadb930a6",
                "boundaryNum": 3,
                "name": "Nsadzo sede",
                "localname": "Nsadzo sede",
                "longitude": null,
                "latitude": null,
                "label": "Posto Administrativo",
                "code": "hadb930a6",
                "children": [
                  {
                    "id": "hd64ca07e",
                    "boundaryNum": 4,
                    "name": "Daissone ",
                    "localname": "Daissone ",
                    "longitude": null,
                    "latitude": null,
                    "label": "Localidade",
                    "code": "hd64ca07e",
                    "children": []
                  },
                  {
                    "id": "h96d5d1c8",
                    "boundaryNum": 4,
                    "name": "Mairrosse",
                    "localname": "Mairrosse",
                    "longitude": null,
                    "latitude": null,
                    "label": "Localidade",
                    "code": "h96d5d1c8",
                    "children": []
                  },
                  {
                    "id": "h66fbf7fa",
                    "boundaryNum": 4,
                    "name": "Nhangawo ",
                    "localname": "Nhangawo ",
                    "longitude": null,
                    "latitude": null,
                    "label": "Localidade",
                    "code": "h66fbf7fa",
                    "children": []
                  },
                  {
                    "id": "h8627da22",
                    "boundaryNum": 4,
                    "name": "Akuse",
                    "localname": "Akuse",
                    "longitude": null,
                    "latitude": null,
                    "label": "Localidade",
                    "code": "h8627da22",
                    "children": []
                  },
                  {
                    "id": "h67585fc2",
                    "boundaryNum": 4,
                    "name": "Caweche ",
                    "localname": "Caweche ",
                    "longitude": null,
                    "latitude": null,
                    "label": "Localidade",
                    "code": "h67585fc2",
                    "children": []
                  },
                  {
                    "id": "h4b37f7ae",
                    "boundaryNum": 4,
                    "name": "Baza ",
                    "localname": "Baza ",
                    "longitude": null,
                    "latitude": null,
                    "label": "Localidade",
                    "code": "h4b37f7ae",
                    "children": []
                  },
                  {
                    "id": "h3d66ae7f",
                    "boundaryNum": 4,
                    "name": "Chansato ",
                    "localname": "Chansato ",
                    "longitude": null,
                    "latitude": null,
                    "label": "Localidade",
                    "code": "h3d66ae7f",
                    "children": []
                  },
                  {
                    "id": "h6b14c25f",
                    "boundaryNum": 4,
                    "name": "Golia ",
                    "localname": "Golia ",
                    "longitude": null,
                    "latitude": null,
                    "label": "Localidade",
                    "code": "h6b14c25f",
                    "children": []
                  },
                  {
                    "id": "h4023ff7d",
                    "boundaryNum": 4,
                    "name": "Sitweia",
                    "localname": "Sitweia",
                    "longitude": null,
                    "latitude": null,
                    "label": "Localidade",
                    "code": "h4023ff7d",
                    "children": []
                  },
                  {
                    "id": "h0a1ec41f",
                    "boundaryNum": 4,
                    "name": "Juliasse",
                    "localname": "Juliasse",
                    "longitude": null,
                    "latitude": null,
                    "label": "Localidade",
                    "code": "h0a1ec41f",
                    "children": []
                  },
                  {
                    "id": "hcbfec3c2",
                    "boundaryNum": 4,
                    "name": "Camba ",
                    "localname": "Camba ",
                    "longitude": null,
                    "latitude": null,
                    "label": "Localidade",
                    "code": "hcbfec3c2",
                    "children": []
                  },
                  {
                    "id": "h35304a71",
                    "boundaryNum": 4,
                    "name": "Chidindi ",
                    "localname": "Chidindi ",
                    "longitude": null,
                    "latitude": null,
                    "label": "Localidade",
                    "code": "h35304a71",
                    "children": []
                  },
                  {
                    "id": "h60d98388",
                    "boundaryNum": 4,
                    "name": "Apezeca",
                    "localname": "Apezeca",
                    "longitude": null,
                    "latitude": null,
                    "label": "Localidade",
                    "code": "h60d98388",
                    "children": []
                  },
                  {
                    "id": "h7e525aff",
                    "boundaryNum": 4,
                    "name": "Palinji ",
                    "localname": "Palinji ",
                    "longitude": null,
                    "latitude": null,
                    "label": "Localidade",
                    "code": "h7e525aff",
                    "children": []
                  },
                  {
                    "id": "h9b33813e",
                    "boundaryNum": 4,
                    "name": "Lambue ",
                    "localname": "Lambue ",
                    "longitude": null,
                    "latitude": null,
                    "label": "Localidade",
                    "code": "h9b33813e",
                    "children": []
                  },
                  {
                    "id": "h3a6cbcf1",
                    "boundaryNum": 4,
                    "name": "Nguenha",
                    "localname": "Nguenha",
                    "longitude": null,
                    "latitude": null,
                    "label": "Localidade",
                    "code": "h3a6cbcf1",
                    "children": []
                  },
                  {
                    "id": "h6971d73b",
                    "boundaryNum": 4,
                    "name": "Moiseis",
                    "localname": "Moiseis",
                    "longitude": null,
                    "latitude": null,
                    "label": "Localidade",
                    "code": "h6971d73b",
                    "children": []
                  },
                  {
                    "id": "h6efc5958",
                    "boundaryNum": 4,
                    "name": "Salirana ",
                    "localname": "Salirana ",
                    "longitude": null,
                    "latitude": null,
                    "label": "Localidade",
                    "code": "h6efc5958",
                    "children": []
                  },
                  {
                    "id": "h5d730908",
                    "boundaryNum": 4,
                    "name": "Campunhica",
                    "localname": "Campunhica",
                    "longitude": null,
                    "latitude": null,
                    "label": "Localidade",
                    "code": "h5d730908",
                    "children": []
                  },
                  {
                    "id": "hccc1c01c",
                    "boundaryNum": 4,
                    "name": "Chilima",
                    "localname": "Chilima",
                    "longitude": null,
                    "latitude": null,
                    "label": "Localidade",
                    "code": "hccc1c01c",
                    "children": []
                  },
                  {
                    "id": "h0a10e99f",
                    "boundaryNum": 4,
                    "name": "Chalesse",
                    "localname": "Chalesse",
                    "longitude": null,
                    "latitude": null,
                    "label": "Localidade",
                    "code": "h0a10e99f",
                    "children": []
                  },
                  {
                    "id": "h374d7abe",
                    "boundaryNum": 4,
                    "name": "Chimate",
                    "localname": "Chimate",
                    "longitude": null,
                    "latitude": null,
                    "label": "Localidade",
                    "code": "h374d7abe",
                    "children": []
                  },
                  {
                    "id": "h544425bc",
                    "boundaryNum": 4,
                    "name": "Wangole",
                    "localname": "Wangole",
                    "longitude": null,
                    "latitude": null,
                    "label": "Localidade",
                    "code": "h544425bc",
                    "children": []
                  },
                  {
                    "id": "h25fa89bb",
                    "boundaryNum": 4,
                    "name": "Conde",
                    "localname": "Conde",
                    "longitude": null,
                    "latitude": null,
                    "label": "Localidade",
                    "code": "h25fa89bb",
                    "children": []
                  },
                  {
                    "id": "h385ba002",
                    "boundaryNum": 4,
                    "name": "Calonga ",
                    "localname": "Calonga ",
                    "longitude": null,
                    "latitude": null,
                    "label": "Localidade",
                    "code": "h385ba002",
                    "children": []
                  },
                  {
                    "id": "h06f75722",
                    "boundaryNum": 4,
                    "name": "Padoco ",
                    "localname": "Padoco ",
                    "longitude": null,
                    "latitude": null,
                    "label": "Localidade",
                    "code": "h06f75722",
                    "children": []
                  },
                  {
                    "id": "h66867928",
                    "boundaryNum": 4,
                    "name": "Sabunete",
                    "localname": "Sabunete",
                    "longitude": null,
                    "latitude": null,
                    "label": "Localidade",
                    "code": "h66867928",
                    "children": []
                  },
                  {
                    "id": "h2b193546",
                    "boundaryNum": 4,
                    "name": "Alfredo ",
                    "localname": "Alfredo ",
                    "longitude": null,
                    "latitude": null,
                    "label": "Localidade",
                    "code": "h2b193546",
                    "children": []
                  },
                  {
                    "id": "h265ad4db",
                    "boundaryNum": 4,
                    "name": "Dogi ",
                    "localname": "Dogi ",
                    "longitude": null,
                    "latitude": null,
                    "label": "Localidade",
                    "code": "h265ad4db",
                    "children": []
                  },
                  {
                    "id": "h083d2c42",
                    "boundaryNum": 4,
                    "name": "Chasanza ",
                    "localname": "Chasanza ",
                    "longitude": null,
                    "latitude": null,
                    "label": "Localidade",
                    "code": "h083d2c42",
                    "children": []
                  },
                  {
                    "id": "h778481c2",
                    "boundaryNum": 4,
                    "name": "Chituculo ",
                    "localname": "Chituculo ",
                    "longitude": null,
                    "latitude": null,
                    "label": "Localidade",
                    "code": "h778481c2",
                    "children": []
                  },
                  {
                    "id": "h25ecfdbd",
                    "boundaryNum": 4,
                    "name": "Linguitone ",
                    "localname": "Linguitone ",
                    "longitude": null,
                    "latitude": null,
                    "label": "Localidade",
                    "code": "h25ecfdbd",
                    "children": []
                  },
                  {
                    "id": "h0d95c6d1",
                    "boundaryNum": 4,
                    "name": "Acufa",
                    "localname": "Acufa",
                    "longitude": null,
                    "latitude": null,
                    "label": "Localidade",
                    "code": "h0d95c6d1",
                    "children": []
                  },
                  {
                    "id": "h7aadfcb1",
                    "boundaryNum": 4,
                    "name": "Cacha",
                    "localname": "Cacha",
                    "longitude": null,
                    "latitude": null,
                    "label": "Localidade",
                    "code": "h7aadfcb1",
                    "children": []
                  }
                ]
              }
            ]
          }
        ]
      }
    },
    {
      "hierarchyType": {
        "code": "ADMIN",
        "name": "ADMIN"
      },
      "boundary": {
        "id": "mz",
        "boundaryNum": 1,
        "name": "MOZAMBIQUE",
        "localname": "MOZAMBIQUE",
        "longitude": null,
        "latitude": null,
        "label": "Country",
        "code": "mz",
        "children": [
          {
            "id": "h5003f843",
            "boundaryNum": 2,
            "name": "Nsadzo",
            "localname": "Nsadzo",
            "longitude": null,
            "latitude": null,
            "label": "Provincia",
            "code": "h5003f843",
            "children": [
              {
                "id": "hadb930a6",
                "boundaryNum": 3,
                "name": "Nsadzo sede",
                "localname": "Nsadzo sede",
                "longitude": null,
                "latitude": null,
                "label": "Posto Administrativo",
                "code": "hadb930a6",
                "children": [
                  {
                    "id": "hd64ca07e",
                    "boundaryNum": 4,
                    "name": "Daissone ",
                    "localname": "Daissone ",
                    "longitude": null,
                    "latitude": null,
                    "label": "Localidade",
                    "code": "hd64ca07e",
                    "children": []
                  },
                  {
                    "id": "h96d5d1c8",
                    "boundaryNum": 4,
                    "name": "Mairrosse",
                    "localname": "Mairrosse",
                    "longitude": null,
                    "latitude": null,
                    "label": "Localidade",
                    "code": "h96d5d1c8",
                    "children": []
                  },
                  {
                    "id": "h66fbf7fa",
                    "boundaryNum": 4,
                    "name": "Nhangawo ",
                    "localname": "Nhangawo ",
                    "longitude": null,
                    "latitude": null,
                    "label": "Localidade",
                    "code": "h66fbf7fa",
                    "children": []
                  },
                  {
                    "id": "h8627da22",
                    "boundaryNum": 4,
                    "name": "Akuse",
                    "localname": "Akuse",
                    "longitude": null,
                    "latitude": null,
                    "label": "Localidade",
                    "code": "h8627da22",
                    "children": []
                  },
                  {
                    "id": "h67585fc2",
                    "boundaryNum": 4,
                    "name": "Caweche ",
                    "localname": "Caweche ",
                    "longitude": null,
                    "latitude": null,
                    "label": "Localidade",
                    "code": "h67585fc2",
                    "children": []
                  },
                  {
                    "id": "h4b37f7ae",
                    "boundaryNum": 4,
                    "name": "Baza ",
                    "localname": "Baza ",
                    "longitude": null,
                    "latitude": null,
                    "label": "Localidade",
                    "code": "h4b37f7ae",
                    "children": []
                  },
                  {
                    "id": "h3d66ae7f",
                    "boundaryNum": 4,
                    "name": "Chansato ",
                    "localname": "Chansato ",
                    "longitude": null,
                    "latitude": null,
                    "label": "Localidade",
                    "code": "h3d66ae7f",
                    "children": []
                  },
                  {
                    "id": "h6b14c25f",
                    "boundaryNum": 4,
                    "name": "Golia ",
                    "localname": "Golia ",
                    "longitude": null,
                    "latitude": null,
                    "label": "Localidade",
                    "code": "h6b14c25f",
                    "children": []
                  },
                  {
                    "id": "h4023ff7d",
                    "boundaryNum": 4,
                    "name": "Sitweia",
                    "localname": "Sitweia",
                    "longitude": null,
                    "latitude": null,
                    "label": "Localidade",
                    "code": "h4023ff7d",
                    "children": []
                  },
                  {
                    "id": "h0a1ec41f",
                    "boundaryNum": 4,
                    "name": "Juliasse",
                    "localname": "Juliasse",
                    "longitude": null,
                    "latitude": null,
                    "label": "Localidade",
                    "code": "h0a1ec41f",
                    "children": []
                  },
                  {
                    "id": "hcbfec3c2",
                    "boundaryNum": 4,
                    "name": "Camba ",
                    "localname": "Camba ",
                    "longitude": null,
                    "latitude": null,
                    "label": "Localidade",
                    "code": "hcbfec3c2",
                    "children": []
                  },
                  {
                    "id": "h35304a71",
                    "boundaryNum": 4,
                    "name": "Chidindi ",
                    "localname": "Chidindi ",
                    "longitude": null,
                    "latitude": null,
                    "label": "Localidade",
                    "code": "h35304a71",
                    "children": []
                  },
                  {
                    "id": "h60d98388",
                    "boundaryNum": 4,
                    "name": "Apezeca",
                    "localname": "Apezeca",
                    "longitude": null,
                    "latitude": null,
                    "label": "Localidade",
                    "code": "h60d98388",
                    "children": []
                  },
                  {
                    "id": "h7e525aff",
                    "boundaryNum": 4,
                    "name": "Palinji ",
                    "localname": "Palinji ",
                    "longitude": null,
                    "latitude": null,
                    "label": "Localidade",
                    "code": "h7e525aff",
                    "children": []
                  },
                  {
                    "id": "h9b33813e",
                    "boundaryNum": 4,
                    "name": "Lambue ",
                    "localname": "Lambue ",
                    "longitude": null,
                    "latitude": null,
                    "label": "Localidade",
                    "code": "h9b33813e",
                    "children": []
                  },
                  {
                    "id": "h3a6cbcf1",
                    "boundaryNum": 4,
                    "name": "Nguenha",
                    "localname": "Nguenha",
                    "longitude": null,
                    "latitude": null,
                    "label": "Localidade",
                    "code": "h3a6cbcf1",
                    "children": []
                  },
                  {
                    "id": "h6971d73b",
                    "boundaryNum": 4,
                    "name": "Moiseis",
                    "localname": "Moiseis",
                    "longitude": null,
                    "latitude": null,
                    "label": "Localidade",
                    "code": "h6971d73b",
                    "children": []
                  },
                  {
                    "id": "h6efc5958",
                    "boundaryNum": 4,
                    "name": "Salirana ",
                    "localname": "Salirana ",
                    "longitude": null,
                    "latitude": null,
                    "label": "Localidade",
                    "code": "h6efc5958",
                    "children": []
                  },
                  {
                    "id": "h5d730908",
                    "boundaryNum": 4,
                    "name": "Campunhica",
                    "localname": "Campunhica",
                    "longitude": null,
                    "latitude": null,
                    "label": "Localidade",
                    "code": "h5d730908",
                    "children": []
                  },
                  {
                    "id": "hccc1c01c",
                    "boundaryNum": 4,
                    "name": "Chilima",
                    "localname": "Chilima",
                    "longitude": null,
                    "latitude": null,
                    "label": "Localidade",
                    "code": "hccc1c01c",
                    "children": []
                  },
                  {
                    "id": "h0a10e99f",
                    "boundaryNum": 4,
                    "name": "Chalesse",
                    "localname": "Chalesse",
                    "longitude": null,
                    "latitude": null,
                    "label": "Localidade",
                    "code": "h0a10e99f",
                    "children": []
                  },
                  {
                    "id": "h374d7abe",
                    "boundaryNum": 4,
                    "name": "Chimate",
                    "localname": "Chimate",
                    "longitude": null,
                    "latitude": null,
                    "label": "Localidade",
                    "code": "h374d7abe",
                    "children": []
                  },
                  {
                    "id": "h544425bc",
                    "boundaryNum": 4,
                    "name": "Wangole",
                    "localname": "Wangole",
                    "longitude": null,
                    "latitude": null,
                    "label": "Localidade",
                    "code": "h544425bc",
                    "children": []
                  },
                  {
                    "id": "h25fa89bb",
                    "boundaryNum": 4,
                    "name": "Conde",
                    "localname": "Conde",
                    "longitude": null,
                    "latitude": null,
                    "label": "Localidade",
                    "code": "h25fa89bb",
                    "children": []
                  },
                  {
                    "id": "h385ba002",
                    "boundaryNum": 4,
                    "name": "Calonga ",
                    "localname": "Calonga ",
                    "longitude": null,
                    "latitude": null,
                    "label": "Localidade",
                    "code": "h385ba002",
                    "children": []
                  },
                  {
                    "id": "h06f75722",
                    "boundaryNum": 4,
                    "name": "Padoco ",
                    "localname": "Padoco ",
                    "longitude": null,
                    "latitude": null,
                    "label": "Localidade",
                    "code": "h06f75722",
                    "children": []
                  },
                  {
                    "id": "h66867928",
                    "boundaryNum": 4,
                    "name": "Sabunete",
                    "localname": "Sabunete",
                    "longitude": null,
                    "latitude": null,
                    "label": "Localidade",
                    "code": "h66867928",
                    "children": []
                  },
                  {
                    "id": "h2b193546",
                    "boundaryNum": 4,
                    "name": "Alfredo ",
                    "localname": "Alfredo ",
                    "longitude": null,
                    "latitude": null,
                    "label": "Localidade",
                    "code": "h2b193546",
                    "children": []
                  },
                  {
                    "id": "h265ad4db",
                    "boundaryNum": 4,
                    "name": "Dogi ",
                    "localname": "Dogi ",
                    "longitude": null,
                    "latitude": null,
                    "label": "Localidade",
                    "code": "h265ad4db",
                    "children": []
                  },
                  {
                    "id": "h083d2c42",
                    "boundaryNum": 4,
                    "name": "Chasanza ",
                    "localname": "Chasanza ",
                    "longitude": null,
                    "latitude": null,
                    "label": "Localidade",
                    "code": "h083d2c42",
                    "children": []
                  },
                  {
                    "id": "h778481c2",
                    "boundaryNum": 4,
                    "name": "Chituculo ",
                    "localname": "Chituculo ",
                    "longitude": null,
                    "latitude": null,
                    "label": "Localidade",
                    "code": "h778481c2",
                    "children": []
                  },
                  {
                    "id": "h25ecfdbd",
                    "boundaryNum": 4,
                    "name": "Linguitone ",
                    "localname": "Linguitone ",
                    "longitude": null,
                    "latitude": null,
                    "label": "Localidade",
                    "code": "h25ecfdbd",
                    "children": []
                  },
                  {
                    "id": "h0d95c6d1",
                    "boundaryNum": 4,
                    "name": "Acufa",
                    "localname": "Acufa",
                    "longitude": null,
                    "latitude": null,
                    "label": "Localidade",
                    "code": "h0d95c6d1",
                    "children": []
                  },
                  {
                    "id": "h7aadfcb1",
                    "boundaryNum": 4,
                    "name": "Cacha",
                    "localname": "Cacha",
                    "longitude": null,
                    "latitude": null,
                    "label": "Localidade",
                    "code": "h7aadfcb1",
                    "children": []
                  }
                ]
              }
            ]
          }
        ]
      }
    }
  ]
}